setup.py
New_packages_on_python1/Binomialdistribution.py
New_packages_on_python1/Gaussiandistribution.py
New_packages_on_python1/Generaldistribution.py
New_packages_on_python1/__init__.py
new_package_on_python1.egg-info/PKG-INFO
new_package_on_python1.egg-info/SOURCES.txt
new_package_on_python1.egg-info/dependency_links.txt
new_package_on_python1.egg-info/not-zip-safe
new_package_on_python1.egg-info/top_level.txt