Metadata-Version: 2.1
Name: new-package-on-python1
Version: 0.1
Summary: Gaussian New_packages_on_python1
Home-page: UNKNOWN
License: UNKNOWN
Platform: UNKNOWN
